Metadata-Version: 2.1
Name: logos-shift-client
Version: 0.11.0
Summary: Switch your current LLM with a finetuned one automatically, no additional latency
Home-page: https://api.bohita.com
Author: Saurabh Bhatnagar
Author-email: saurabh@virevol.com
Project-URL: Homepage, https://api.bohita.com
Project-URL: Repository, https://github.com/virevolai/logos-shift-client
Classifier: Programming Language :: Python :: 3
Classifier: License :: OSI Approved :: MIT License
Classifier: Topic :: Scientific/Engineering :: Artificial Intelligence
Classifier: Topic :: Text Processing :: Linguistic
Classifier: Topic :: Software Development :: Libraries :: Application Frameworks
Classifier: Framework :: AsyncIO
License-File: LICENSE
Requires-Dist: requests
Requires-Dist: asyncio
Requires-Dist: tenacity
Requires-Dist: httpx
Provides-Extra: dev
Requires-Dist: pytest ; extra == 'dev'
Requires-Dist: ruff >=0.1.2 ; extra == 'dev'
Requires-Dist: bump2version ==1.0.1 ; extra == 'dev'
